{
  "materials": [
    {
      "materialGroupName": "Aluminium Plate PA4",
      "type": "Plate",
      "image": "https://a.allegroimg.com/s512/11e076/b8a814b14946a0413afa17dd2ca9/PLASKOWNIK-aluminiowa-250x270-gr-25mm-FORMATKA-Pa4",
      "material": {
        "name": "Acetal (POM)",
        "density": 1.41
      },
      "id": 1,
      "materialList": [
        {
          "pricePerKg": 10,
          "min_quantity": 11,
          "quantity": 11,
          "z": 10,
          "y": 575,
          "x": 415,
          "id": 1,
          "diameter": "",
          "thickeness": "",
          "length": "",
          "name": "Aluminium Plate PA4: 10x415x575",
          "price": "33.60"
        }
      ]
    }
  ],
  "tools": [
    {
      "toolGroupName": "asdad",
      "image": "",
      "toolList": [
        {
          "name": "gówno",
          "id": 1,
          "dc": 12,
          "cfl": 12,
          "oal": 12,
          "quantity": 12,
          "min_quantity": 12,
          "price": 12,
          "tool_id": "",
          "e_shop_link": ""
        },
        {
          "name": "END MILL VF5",
          "id": 2,
          "dc": 12,
          "cfl": 12,
          "oal": 12,
          "quantity": 12,
          "min_quantity": 12,
          "price": 12,
          "tool_id": "asdasd",
          "e_shop_link": "asdasd"
        }
      ],
      "id": 1
    },
    {
      "toolGroupName": "WIertla",
      "image": "",
      "toolList": [],
      "id": 2
    }
  ],
  "recycle": [],
  "supplier": [],
  "user": [
    {
      "id": 1,
      "name": "Jan",
      "surname": "Kowalski",
      "email": "jan.kowalski@example.com",
      "phone": "123456789",
      "isAdmin": true,
      "isBLocked": false
    }
  ],
  "calculation": [
    {
      "shiftLength": 8,
      "numberOfMachines": 1,
      "hourlyRate": 0,
      "income": 0,
      "toolCost": 0,
      "materialCost": 0,
      "factor": 1.2,
      "camTime": 0,
      "variableCostsII": 0,
      "variableCostsI": 0,
      "leasingPrice": 0,
      "toolsPrice": 500,
      "depreciationPrice": 1000,
      "mediaPrice": 1000,
      "pricePerKwh": 0.79,
      "operatingHours": 160,
      "powerConsumption": 45,
      "employeeCosts": 45000,
      "status": "Pending",
      "selectedDate": "Wed, 24 May 2023 16:34:11 GMT",
      "calculationName": "123",
      "id": 1
    },
    {
      "shiftLength": 8,
      "numberOfMachines": 1,
      "hourlyRate": 0,
      "income": 0,
      "toolCost": 0,
      "materialCost": 0,
      "factor": 1.2,
      "camTime": 0,
      "variableCostsII": 0,
      "variableCostsI": 0,
      "leasingPrice": 0,
      "toolsPrice": 500,
      "depreciationPrice": 1000,
      "mediaPrice": 1000,
      "pricePerKwh": 0.79,
      "operatingHours": 160,
      "powerConsumption": 45,
      "employeeCosts": 45000,
      "status": "Pending",
      "selectedDate": "24/05/2023",
      "calculationName": "test2",
      "id": 2
    },
    {
      "shiftLength": 8,
      "numberOfMachines": 1,
      "hourlyRate": 0,
      "income": 0,
      "toolCost": 0,
      "materialCost": 0,
      "factor": 1.2,
      "camTime": 1,
      "variableCostsII": 0,
      "variableCostsI": 0,
      "leasingPrice": 0,
      "toolsPrice": 500,
      "depreciationPrice": 1000,
      "mediaPrice": 1000,
      "pricePerKwh": 0.79,
      "operatingHours": 160,
      "powerConsumption": 45,
      "employeeCosts": 45000,
      "status": "Pending",
      "selectedDate": "24/05/2023",
      "calculationName": "test3",
      "id": 3
    }
  ]
}
